docs/__init__.py
scSAMP/__init__.py
scSAMP/_config.py
scSAMP/_decorator.py
scSAMP/_utils.py
scSAMP/config.py
scSAMP/decorator.py
scSAMP/utils.py
scSAMP/evaluation/__init__.py
scSAMP/evaluation/_batch.py
scSAMP/evaluation/_score.py
scSAMP/evaluation/eval.py
scSAMP/evaluation/score.py
scSAMP/evaluation/model/__init__.py
scSAMP/evaluation/model/_actinn.py
scSAMP/evaluation/model/actinn.py
scSAMP/processing/__init__.py
scSAMP/processing/_balance.py
scSAMP/processing/_factors.py
scSAMP/processing/_preprocessing.py
scSAMP/processing/_sampler.py
scSAMP/processing/balance.py
scSAMP/processing/factors.py
scSAMP/processing/preprocessing.py
scSAMP/processing/sampler.py
scSAMP-0.1.5.dist-info/LICENSE
scSAMP-0.1.5.dist-info/METADATA
scSAMP-0.1.5.dist-info/WHEEL
scSAMP-0.1.5.dist-info/top_level.txt
scSAMP-0.1.5.dist-info/RECORD
